[
  {
    "title": "iPhone 13 pro",
    "model": "iphone 13 pro pro",
    "storage": null,
    "price": 130.0,
    "market_price": 370.0,
    "profit": 138.1,
    "score": 26.0,
    "confidence": 20.0,
    "level": "A级",
    "url": "https://www.subito.it/telefonia/iphone-13-pro-cosenza-644198027.htm",
    "source": "SUBITO",
    "decision": "SKIP",
    "risk": "MEDIUM",
    "sell_time": "3-5 days",
    "invest_eur": 0
  },
  {
    "title": "Fotocamere posteriori ORIGINALI iPhone  14 Max",
    "model": "iphone 14",
    "storage": null,
    "price": 120.0,
    "market_price": 294.99,
    "profit": 90.7,
    "score": 26.0,
    "confidence": 20.0,
    "level": "A级",
    "url": "https://www.subito.it/telefonia/fotocamere-posteriori-originali-iphone-14-max-palermo-644225116.htm",
    "source": "SUBITO",
    "decision": "SKIP",
    "risk": "MEDIUM",
    "sell_time": "3-5 days",
    "invest_eur": 0
  },
  {
    "title": "iPhone 14 pro 128 gb",
    "model": "iphone 14 pro pro",
    "storage": 128,
    "price": 250.0,
    "market_price": 450.0,
    "profit": 79.2,
    "score": 46.0,
    "confidence": 20.0,
    "level": "B级",
    "url": "https://www.subito.it/telefonia/iphone-14-pro-128-gb-roma-644191298.htm",
    "source": "SUBITO",
    "decision": "BUY",
    "risk": "MEDIUM",
    "sell_time": "2-3 days",
    "invest_eur": 250.0
  },
  {
    "title": "Iphone 13 pro 128gb tutto originale",
    "model": "iphone 13 pro pro",
    "storage": 128,
    "price": 200.0,
    "market_price": 370.0,
    "profit": 68.1,
    "score": 46.0,
    "confidence": 20.0,
    "level": "B级",
    "url": "https://www.subito.it/telefonia/iphone-13-pro-128gb-tutto-originale-napoli-644148667.htm",
    "source": "SUBITO",
    "decision": "SKIP",
    "risk": "MEDIUM",
    "sell_time": "2-3 days",
    "invest_eur": 0
  },
  {
    "title": "Iphone 13 128 gb",
    "model": "iphone 13",
    "storage": 128,
    "price": 130.0,
    "market_price": 271.0,
    "profit": 62.3,
    "score": 46.0,
    "confidence": 20.0,
    "level": "B级",
    "url": "https://www.subito.it/telefonia/iphone-13-128-gb-roma-644153571.htm",
    "source": "SUBITO",
    "decision": "SKIP",
    "risk": "MEDIUM",
    "sell_time": "2-3 days",
    "invest_eur": 0
  },
  {
    "title": "Iphone 14 PRO 128GB IMPECCABILE!!",
    "model": "iphone 14 pro pro",
    "storage": 128,
    "price": 270.0,
    "market_price": 450.0,
    "profit": 59.2,
    "score": 76.0,
    "confidence": 20.0,
    "level": "B级",
    "url": "https://www.subito.it/telefonia/iphone-14-pro-128gb-impeccabile-napoli-644275280.htm",
    "source": "SUBITO",
    "decision": "SKIP",
    "risk": "MEDIUM",
    "sell_time": "2-3 days",
    "invest_eur": 0
  },
  {
    "title": "iPhone 12.",
    "model": "iphone 12",
    "storage": null,
    "price": 90.0,
    "market_price": 174.99,
    "profit": 28.9,
    "score": 16.0,
    "confidence": 20.0,
    "level": "C级",
    "url": "https://www.subito.it/telefonia/iphone-12-padova-644232731.htm",
    "source": "SUBITO",
    "decision": "SKIP",
    "risk": "MEDIUM",
    "sell_time": "3-5 days",
    "invest_eur": 0
  },
  {
    "title": "iPhone 12Pro128GB Grigio Siderale",
    "model": "iphone 12 pro pro",
    "storage": 128,
    "price": 200.0,
    "market_price": 314.99,
    "profit": 26.0,
    "score": 36.0,
    "confidence": 20.0,
    "level": "C级",
    "url": "https://www.subito.it/telefonia/iphone-12pro128gb-grigio-siderale-sud-sardegna-644223445.htm",
    "source": "SUBITO",
    "decision": "SKIP",
    "risk": "MEDIUM",
    "sell_time": "3-5 days",
    "invest_eur": 0
  },
  {
    "title": "Smartphone Iphone 12 pro 256gb ",
    "model": "iphone 12 pro pro",
    "storage": 256,
    "price": 200.0,
    "market_price": 314.99,
    "profit": 26.0,
    "score": 36.0,
    "confidence": 20.0,
    "level": "C级",
    "url": "https://www.subito.it/telefonia/smartphone-iphone-12-pro-256gb-salerno-644228319.htm",
    "source": "SUBITO",
    "decision": "SKIP",
    "risk": "MEDIUM",
    "sell_time": "3-5 days",
    "invest_eur": 0
  },
  {
    "title": "Apple iPhone 12 Pro 128GB💫",
    "model": "iphone 12 pro pro",
    "storage": 128,
    "price": 201.0,
    "market_price": 314.99,
    "profit": 25.0,
    "score": 36.0,
    "confidence": 20.0,
    "level": "C级",
    "url": "https://www.subito.it/telefonia/apple-iphone-12-pro-128gb-parma-644161580.htm",
    "source": "SUBITO",
    "decision": "SKIP",
    "risk": "MEDIUM",
    "sell_time": "3-5 days",
    "invest_eur": 0
  },
  {
    "title": "Apple Iphone 13 128 gb",
    "model": "iphone 13",
    "storage": 128,
    "price": 170.0,
    "market_price": 271.0,
    "profit": 22.3,
    "score": 36.0,
    "confidence": 20.0,
    "level": "C级",
    "url": "https://www.subito.it/telefonia/apple-iphone-13-128-gb-torino-644202635.htm",
    "source": "SUBITO",
    "decision": "SKIP",
    "risk": "MEDIUM",
    "sell_time": "3-5 days",
    "invest_eur": 0
  },
  {
    "title": "Iphone 14 Midnight - 128 giga",
    "model": "iphone 14",
    "storage": 128,
    "price": 190.0,
    "market_price": 294.99,
    "profit": 20.7,
    "score": 36.0,
    "confidence": 20.0,
    "level": "C级",
    "url": "https://www.subito.it/telefonia/iphone-14-midnight-128-giga-lecce-644189778.htm",
    "source": "SUBITO",
    "decision": "SKIP",
    "risk": "MEDIUM",
    "sell_time": "3-5 days",
    "invest_eur": 0
  },
  {
    "title": "Iphone 13 pro 1tb",
    "model": "iphone 13 pro pro",
    "storage": 1024,
    "price": 249.0,
    "market_price": 370.0,
    "profit": 19.1,
    "score": 36.0,
    "confidence": 20.0,
    "level": "C级",
    "url": "https://www.subito.it/telefonia/iphone-13-pro-1tb-palermo-644159119.htm",
    "source": "SUBITO",
    "decision": "SKIP",
    "risk": "MEDIUM",
    "sell_time": "3-5 days",
    "invest_eur": 0
  },
  {
    "title": "iPhone 12",
    "model": "iphone 12",
    "storage": null,
    "price": 100.0,
    "market_price": 174.99,
    "profit": 18.9,
    "score": 16.0,
    "confidence": 20.0,
    "level": "C级",
    "url": "https://www.subito.it/telefonia/iphone-12-napoli-644230161.htm",
    "source": "SUBITO",
    "decision": "SKIP",
    "risk": "MEDIUM",
    "sell_time": "3-5 days",
    "invest_eur": 0
  },
  {
    "title": "IPHONE 13 PRO 128GB",
    "model": "iphone 13 pro pro",
    "storage": 128,
    "price": 250.0,
    "market_price": 370.0,
    "profit": 18.1,
    "score": 36.0,
    "confidence": 20.0,
    "level": "C级",
    "url": "https://www.subito.it/telefonia/iphone-13-pro-128gb-bologna-644186583.htm",
    "source": "SUBITO",
    "decision": "SKIP",
    "risk": "MEDIUM",
    "sell_time": "3-5 days",
    "invest_eur": 0
  },
  {
    "title": "Apple iPhone 12 Pro 128GB💫",
    "model": "iphone 12 pro pro",
    "storage": 128,
    "price": 209.0,
    "market_price": 314.99,
    "profit": 17.0,
    "score": 36.0,
    "confidence": 20.0,
    "level": "C级",
    "url": "https://www.subito.it/telefonia/apple-iphone-12-pro-128gb-parma-644158746.htm",
    "source": "SUBITO",
    "decision": "SKIP",
    "risk": "MEDIUM",
    "sell_time": "3-5 days",
    "invest_eur": 0
  },
  {
    "title": "Iphone 13 - 128 GB",
    "model": "iphone 13",
    "storage": 128,
    "price": 180.0,
    "market_price": 271.0,
    "profit": 12.3,
    "score": 36.0,
    "confidence": 20.0,
    "level": "C级",
    "url": "https://www.subito.it/telefonia/iphone-13-128-gb-ancona-644216270.htm",
    "source": "SUBITO",
    "decision": "SKIP",
    "risk": "MEDIUM",
    "sell_time": "3-5 days",
    "invest_eur": 0
  },
  {
    "title": "IPhone 12 Pro 128GB",
    "model": "iphone 12 pro pro",
    "storage": 128,
    "price": 220.0,
    "market_price": 314.99,
    "profit": 6.0,
    "score": 36.0,
    "confidence": 20.0,
    "level": "C级",
    "url": "https://www.subito.it/telefonia/iphone-12-pro-128gb-benevento-644208951.htm",
    "source": "SUBITO",
    "decision": "SKIP",
    "risk": "MEDIUM",
    "sell_time": "3-5 days",
    "invest_eur": 0
  }
]